rooguys/__init__.py
rooguys/client.py
rooguys/errors.py
rooguys/http_client.py
rooguys/tests/__init__.py
rooguys/tests/fixtures/__init__.py
rooguys/tests/fixtures/responses.py
rooguys/tests/property/__init__.py
rooguys/tests/property/test_request_construction.py
rooguys/tests/property/test_response_parsing.py
rooguys/tests/property/test_sdk_modules.py
rooguys/tests/unit/__init__.py
rooguys/tests/unit/test_aha.py
rooguys/tests/unit/test_badges.py
rooguys/tests/unit/test_config.py
rooguys/tests/unit/test_errors.py
rooguys/tests/unit/test_events.py
rooguys/tests/unit/test_leaderboards.py
rooguys/tests/unit/test_levels.py
rooguys/tests/unit/test_questionnaires.py
rooguys/tests/unit/test_users.py
rooguys/tests/utils/__init__.py
rooguys/tests/utils/generators.py
rooguys/tests/utils/mock_client.py
rooguys-1.0.0.dist-info/METADATA
rooguys-1.0.0.dist-info/WHEEL
rooguys-1.0.0.dist-info/top_level.txt
rooguys-1.0.0.dist-info/RECORD
