Metadata-Version: 2.4
Name: rooguys
Version: 1.0.0
Summary: Official Python SDK for Rooguys API
Author-email: "@mowamed" <support@rooguys.com>
Project-URL: Homepage, https://github.com/rooguys/rooguys-python
Project-URL: Bug Tracker, https://github.com/rooguys/rooguys-python/issues
Classifier: Programming Language :: Python :: 3
Classifier: License :: OSI Approved :: MIT License
Classifier: Operating System :: OS Independent
Requires-Python: >=3.7
Requires-Dist: requests>=2.25.0
Provides-Extra: dev
Requires-Dist: pytest>=7.0.0; extra == "dev"
Requires-Dist: pytest-cov>=4.1.0; extra == "dev"
Requires-Dist: pytest-mock>=3.12.0; extra == "dev"
Requires-Dist: requests-mock>=1.10.0; extra == "dev"
Requires-Dist: hypothesis>=6.92.0; extra == "dev"
